tgcrawler/__init__.py
tgcrawler/utils.py
tg_crawler-1.0.0.dist-info/LICENSE
tg_crawler-1.0.0.dist-info/METADATA
tg_crawler-1.0.0.dist-info/WHEEL
tg_crawler-1.0.0.dist-info/entry_points.txt
tg_crawler-1.0.0.dist-info/RECORD
