Metadata-Version: 2.1
Name: tg-crawler
Version: 1.0.0
Summary: 💾 Daemon to download/upload telegram files.
Home-page: https://github.com/SantiiRepair/tg-crawler
License: GPL-3.0
Author: Santiago Ramirez
Author-email: santiirepair@gmail.com
Requires-Python: >=3.10,<3.13
Classifier: License :: OSI Approved :: GNU General Public License v3 (GPLv3)
Classifier: Programming Language :: Python :: 3
Classifier: Programming Language :: Python :: 3.10
Classifier: Programming Language :: Python :: 3.11
Requires-Dist: click (==8.1.7)
Requires-Dist: colorama (>=0.4.6)
Requires-Dist: pyrogram (>=2.0.106)
Requires-Dist: shutup (==0.2.0)
Requires-Dist: termcolor (==2.3.0)
Requires-Dist: tgcrypto (>=1.2.5)
Requires-Dist: tqdm (>=4.66.1)
Project-URL: Repository, https://github.com/SantiiRepair/tg-crawler
